{
  "policies": {
    "Homepage": {
      "URL": "https://rescuezilla.com",
      "Additional": [ "https://github.com/rescuezilla/rescuezilla" ]
    },
    "DontCheckDefaultBrowser": true,
    "DisableTelemetry": true, 
    "DisableProfileImport": true,
    "OfferToSaveLogins": false,
    "NewTabPage": false, 
    "OverrideFirstRunPage": "",
    "OverridePostUpdatePage": "",
    "Preferences": {
      "browser.tabs.warnOnClose": false
    },
    "Bookmarks": {
      "DisplayBookmarksToolbar": false,
      "NoDefaultBookmarks": true
    }
  }
}
